LICENSE
MANIFEST.in
README.md
setup.py
jupyterhub_ldapauthenticator_refresh.egg-info/PKG-INFO
jupyterhub_ldapauthenticator_refresh.egg-info/SOURCES.txt
jupyterhub_ldapauthenticator_refresh.egg-info/dependency_links.txt
jupyterhub_ldapauthenticator_refresh.egg-info/requires.txt
jupyterhub_ldapauthenticator_refresh.egg-info/top_level.txt
ldapauthenticator/__init__.py
ldapauthenticator/ldapauthenticator.py