Metadata-Version: 2.1
Name: jupyterhub-ldapauthenticator-refresh
Version: 1.3.3.dev0
Summary: LDAP Authenticator for JupyterHub
Home-page: https://github.com/Litzuck/ldapauthenticator
Author: Oliver Traub
Author-email: oliver.traub@datev.de
License: 3 Clause BSD
Platform: UNKNOWN
